README.md
setup.py
test/test_call_ordering.py
test/test_future.py
test/test_process_executor.py
test/test_thread_executor.py
test/test_unsync.py
unsync/__init__.py
unsync/unsync.py
unsync.egg-info/PKG-INFO
unsync.egg-info/SOURCES.txt
unsync.egg-info/dependency_links.txt
unsync.egg-info/top_level.txt