Metadata-Version: 1.0
Name: unsync
Version: 1.0
Summary: Unsynchronize asyncio
Home-page: https://github.com/alex-sherman/unsync
Author: Alex-Sherman
Author-email: asherman1024@gmail.com
License: MIT
Platform: UNKNOWN
